vizer/control.py
vizer/graph.py
vizer/gui.py
vizer/ids.py
vizer/main.py
vizer/utils.py
vizer/workspace.py
vizu-0.1.7.dist-info/METADATA
vizu-0.1.7.dist-info/WHEEL
vizu-0.1.7.dist-info/entry_points.txt
vizu-0.1.7.dist-info/top_level.txt
vizu-0.1.7.dist-info/RECORD
