Metadata-Version: 2.1
Name: vizu
Version: 0.1.7
Summary: Visualization of data files
Home-page: https://github.com/gedemagt/vizer
Author: Jesper Halkjær Jensen
Author-email: mail@jeshj.com
License: MIT
Platform: UNKNOWN
Requires-Python: >=3.6
Requires-Dist: flask>=3.0.0
Requires-Dist: pandas>=2.0.0
Requires-Dist: scipy>=1.14.0
Requires-Dist: dash>=2.15.0
Requires-Dist: dash-extensions>=1.0.0
Requires-Dist: dash-bootstrap-components==1.6.0
Requires-Dist: dash-table==5.0.0
Requires-Dist: watchdog>=5.0.0
